gateway/__init__.py
gateway/client.py
gateway/builders/__init__.py
gateway/builders/authorization_builder.py
gateway/builders/command_data_builder.py
gateway/builders/customer_data_builder.py
gateway/builders/info_data_builder.py
gateway/builders/merchant_order_builder.py
gateway/builders/money_data_builder.py
gateway/builders/payment_data_builder.py
gateway/builders/report_filter_data_builder.py
gateway/builders/system_data_builder.py
gateway/builders/transaction_builder.py
gateway/builders/verify_3d_enrollment_builder.py
gateway/builders/verify_card_data_builder.py
gateway/crypto/__init__.py
gateway/crypto/digest.py
gateway/data_sets/__init__.py
gateway/data_sets/request_parameters.py
gateway/operations/__init__.py
gateway/operations/operations.py
gateway/responses/__init__.py
gateway/responses/constants.py
gateway/responses/csv_response.py
gateway/responses/enrollment.py
gateway/responses/generic.py
gateway/responses/limits.py
gateway/responses/lists.py
gateway/responses/parts.py
gateway/responses/payment.py
gateway/responses/response.py
gateway/transport/__init__.py
gateway/transport/transport.py
gateway/utils/__init__.py
gateway/utils/data_structures.py
gateway/utils/data_validator.py
tests/__init__.py
tests/test_client.py
tests/builders/__init__.py
tests/builders/test_authorization_builder.py
tests/builders/test_command_data_builder.py
tests/builders/test_customer_data_builder.py
tests/builders/test_info_data_builder.py
tests/builders/test_merchant_order_builder.py
tests/builders/test_money_data_builder.py
tests/builders/test_payment_data_builder.py
tests/builders/test_report_filter_data_builder.py
tests/builders/test_system_data_builder.py
tests/builders/test_transaction_builder.py
tests/builders/test_verify_3d_enrollment_builder.py
tests/builders/test_verify_card_data_builder.py
tests/crypro/__init__.py
tests/crypro/test_digest.py
tests/operations/__init__.py
tests/operations/test_operations.py
tests/responses/__init__.py
tests/responses/test_response.py
transactpro_gw3_client-1.7.8.dist-info/LICENSE
transactpro_gw3_client-1.7.8.dist-info/METADATA
transactpro_gw3_client-1.7.8.dist-info/WHEEL
transactpro_gw3_client-1.7.8.dist-info/top_level.txt
transactpro_gw3_client-1.7.8.dist-info/RECORD
