Metadata-Version: 2.1
Name: transactpro-gw3-client
Version: 1.7.8
Summary: Transact PRO Gateway3 implementation in Python.
Home-page: https://github.com/TransactPRO/gw3-python-client
Author: Transact Pro
Author-email: support@transactpro.net
License: MIT
Keywords: GW3 gateway3 integration gateway TransactPRO python python3
Classifier: Development Status :: 5 - Production/Stable
Classifier: Intended Audience :: Developers
Classifier: License :: OSI Approved :: MIT License
Classifier: Natural Language :: English
Classifier: Operating System :: OS Independent
Classifier: Programming Language :: Python
Classifier: Programming Language :: Python :: 3
Classifier: Programming Language :: Python :: 3.6
Classifier: Programming Language :: Python :: 3.7
Classifier: Programming Language :: Python :: 3.8
Classifier: Programming Language :: Python :: 3.9
Classifier: Programming Language :: Python :: 3.10
Classifier: Programming Language :: Python :: 3.11
Classifier: Topic :: Software Development :: Libraries :: Python Modules
Requires-Python: >=3.6
License-File: LICENSE
Requires-Dist: requests
